Workbook

Sheet Financial Data
A1: Company Name: | B1: DXone ERP
A2: Financial Year Start: | B2: January
A5: Classification | B5: Account Name | C5: 45627 | D5: Jan 2025 | E5: Feb 2025 | F5: Mar 2025 | G5: Apr 2025 | H5: May 2025
B6: Revenue
A7: REV | B7: DXOne ERP - Licence Tier 3 | C7: 63393.16 | D7: =Sheet1!C5 -> 5813.85 | E7: =Sheet1!D5 -> 5813.85 | F7: =Sheet1!E5 -> 5873.85 | G7: =Sheet1!F5 -> 5873.85 | H7: =Sheet1!G5 -> 5248.18
A8: REV | B8: Other Optional Suites | D8: =VLOOKUP($B8,Sheet1!$B$2:$G$52,MATCH('Financial Data'!D$5,Sheet1!$B$2:$G$2,0),0) -> 0 | E8: =VLOOKUP($B8,Sheet1!$B$2:$G$52,MATCH('Financial Data'!E$5,Sheet1!$B$2:$G$2,0),0) -> 0 | F8: =VLOOKUP($B8,Sheet1!$B$2:$G$52,MATCH('Financial Data'!F$5,Sheet1!$B$2:$G$2,0),0) -> 0 | G8: =VLOOKUP($B8,Sheet1!$B$2:$G$52,MATCH('Financial Data'!G$5,Sheet1!$B$2:$G$2,0),0) -> 0 | H8: =VLOOKUP($B8,Sheet1!$B$2:$G$52,MATCH('Financial Data'!H$5,Sheet1!$B$2:$G$2,0),0) -> 0
A9: REV | B9: DCA Monitoring | C9: 9788.82 | D9: =VLOOKUP($B9,Sheet1!$B$2:$G$52,MATCH('Financial Data'!D$5,Sheet1!$B$2:$G$2,0),0) -> 0 | E9: =VLOOKUP($B9,Sheet1!$B$2:$G$52,MATCH('Financial Data'!E$5,Sheet1!$B$2:$G$2,0),0) -> 0 | F9: =VLOOKUP($B9,Sheet1!$B$2:$G$52,MATCH('Financial Data'!F$5,Sheet1!$B$2:$G$2,0),0) -> 0 | G9: =VLOOKUP($B9,Sheet1!$B$2:$G$52,MATCH('Financial Data'!G$5,Sheet1!$B$2:$G$2,0),0) -> 0 | H9: =VLOOKUP($B9,Sheet1!$B$2:$G$52,MATCH('Financial Data'!H$5,Sheet1!$B$2:$G$2,0),0) -> 0
A10: REV | B10: Implementation | C10: 5912.39 | D10: =VLOOKUP($B10,Sheet1!$B$2:$G$52,MATCH('Financial Data'!D$5,Sheet1!$B$2:$G$2,0),0) -> 0 | E10: =VLOOKUP($B10,Sheet1!$B$2:$G$52,MATCH('Financial Data'!E$5,Sheet1!$B$2:$G$2,0),0) -> 0 | F10: =VLOOKUP($B10,Sheet1!$B$2:$G$52,MATCH('Financial Data'!F$5,Sheet1!$B$2:$G$2,0),0) -> 0 | G10: =VLOOKUP($B10,Sheet1!$B$2:$G$52,MATCH('Financial Data'!G$5,Sheet1!$B$2:$G$2,0),0) -> 0 | H10: =VLOOKUP($B10,Sheet1!$B$2:$G$52,MATCH('Financial Data'!H$5,Sheet1!$B$2:$G$2,0),0) -> 0
A11: REV | B11: Implementation Tier 3 | C11: 62.43 | D11: =Sheet1!C9 -> 0 | E11: =Sheet1!D9 -> 0 | F11: =Sheet1!E9 -> 0 | G11: =Sheet1!F9 -> 0 | H11: =Sheet1!G9 -> 0
A12: REV | B12: Discounts | C12: 3845.54 | D12: =VLOOKUP($B12,Sheet1!$B$2:$G$52,MATCH('Financial Data'!D$5,Sheet1!$B$2:$G$2,0),0) -> 0 | E12: =VLOOKUP($B12,Sheet1!$B$2:$G$52,MATCH('Financial Data'!E$5,Sheet1!$B$2:$G$2,0),0) -> 0 | F12: =VLOOKUP($B12,Sheet1!$B$2:$G$52,MATCH('Financial Data'!F$5,Sheet1!$B$2:$G$2,0),0) -> 0 | G12: =VLOOKUP($B12,Sheet1!$B$2:$G$52,MATCH('Financial Data'!G$5,Sheet1!$B$2:$G$2,0),0) -> 0 | H12: =VLOOKUP($B12,Sheet1!$B$2:$G$52,MATCH('Financial Data'!H$5,Sheet1!$B$2:$G$2,0),0) -> 0
A13: REV | B13: Customer Discounts | C13: 2531.46 | D13: =VLOOKUP($B13,Sheet1!$B$2:$G$52,MATCH('Financial Data'!D$5,Sheet1!$B$2:$G$2,0),0) -> -565.67 | E13: =VLOOKUP($B13,Sheet1!$B$2:$G$52,MATCH('Financial Data'!E$5,Sheet1!$B$2:$G$2,0),0) -> -565.67 | F13: =VLOOKUP($B13,Sheet1!$B$2:$G$52,MATCH('Financial Data'!F$5,Sheet1!$B$2:$G$2,0),0) -> -565.67 | G13: =VLOOKUP($B13,Sheet1!$B$2:$G$52,MATCH('Financial Data'!G$5,Sheet1!$B$2:$G$2,0),0) -> -565.67 | H13: =VLOOKUP($B13,Sheet1!$B$2:$G$52,MATCH('Financial Data'!H$5,Sheet1!$B$2:$G$2,0),0) -> 0
B14: Cost of Sales | C14: 2149.91
A15: VCOS | B15: Implementation Costs | C15: 773.08 | D15: =Sheet1!C13 -> 0 | E15: =Sheet1!D13 -> 0 | F15: =Sheet1!E13 -> 0 | G15: =Sheet1!F13 -> 0 | H15: =Sheet1!G13 -> 0
A16: VCOS | B16: Implementation Payroll & Employee Expenses | D16: =Sheet1!C14 -> 0 | E16: =Sheet1!D14 -> 0 | F16: =Sheet1!E14 -> 0 | G16: =Sheet1!F14 -> 0 | H16: =Sheet1!G14 -> 0
A17: VCOS | B17: =Sheet1!B15 -> Payroll Expenses (Implementation) | C17: 200 | D17: =Sheet1!C15 -> 24418.58 | E17: =Sheet1!D15 -> 16601.56 | F17: =Sheet1!E15 -> 16491.56 | G17: =Sheet1!F15 -> 7355.78 | H17: =Sheet1!G15 -> 0
A18: VCOS | B18: =Sheet1!B16 -> Payroll Taxes (Implementation) | C18: 15 | D18: =Sheet1!C16 -> 1633.08 | E18: =Sheet1!D16 -> 1197.09 | F18: =Sheet1!E16 -> 1189.45 | G18: =Sheet1!F16 -> 594.72 | H18: =Sheet1!G16 -> 0
A19: VCOS | B19: Server Hosting Charges | C19: 99.01 | D19: =Sheet1!C17 -> 1364.26 | E19: =Sheet1!D17 -> 1530.25 | F19: =Sheet1!E17 -> 2616.47 | G19: =Sheet1!F17 -> 1600.58 | H19: =Sheet1!G17 -> 1596.51
A20: VCOS | B20: Customer Success Payroll & Employee Expenses | C20: 0 | D20: =Sheet1!C18 -> 0 | E20: =Sheet1!D18 -> 0 | F20: =Sheet1!E18 -> 0 | G20: =Sheet1!F18 -> 0 | H20: =Sheet1!G18 -> 0
A21: VCOS | B21: Payroll Expenses (Customer Success) | C21: 66.48 | D21: =Sheet1!C19 -> 2957.89 | E21: =Sheet1!D19 -> 2203.27 | F21: =Sheet1!E19 -> 2175.77 | G21: =Sheet1!F19 -> 865.39 | H21: =Sheet1!G19 -> 0
A22: VCOS | B22: Payroll Taxes (Customer Success) | C22: 164.98 | D22: =Sheet1!C20 -> 184.54 | E22: =Sheet1!D20 -> 141.48 | F22: =Sheet1!E20 -> 142.25 | G22: =Sheet1!F20 -> 71.13 | H22: =Sheet1!G20 -> 0
B23: Expenses | C23: 10880
A24: FEXP | B24: Sales and Marketing Costs | C24: 15.21 | D24: =Sheet1!C22 -> 0 | E24: =Sheet1!D22 -> 0 | F24: =Sheet1!E22 -> 0 | G24: =Sheet1!F22 -> 0 | H24: =Sheet1!G22 -> 0
A25: FEXP | B25: Operating Payroll & Employee Expenses | C25: 29.88 | D25: =Sheet1!C23 -> 0 | E25: =Sheet1!D23 -> 0 | F25: =Sheet1!E23 -> 0 | G25: =Sheet1!F23 -> 28172.03 | H25: =Sheet1!G23 -> 56579.49
A26: FEXP | B26: Payroll Expenses (Operating) | C26: 0 | D26: =Sheet1!C24 -> 5346.16 | E26: =Sheet1!D24 -> 3846.15 | F26: =Sheet1!E24 -> 5328 | G26: =Sheet1!F24 -> 1923.08 | H26: =Sheet1!G24 -> 0
A27: FEXP | B27: Payroll Taxes (Operating) | C27: 0 | D27: =Sheet1!C25 -> 360.62 | E27: =Sheet1!D25 -> 339.61 | F27: =Sheet1!E25 -> 343.46 | G27: =Sheet1!F25 -> 171.73 | H27: =Sheet1!G25 -> 0
A28: FEXP | B28: Employee Benefits & Insurance Expense | C28: 1492.31 | D28: =Sheet1!C26 -> 0 | E28: =Sheet1!D26 -> 0 | F28: =Sheet1!E26 -> 1001 | G28: =Sheet1!F26 -> 1001 | H28: =Sheet1!G26 -> 0
A29: FEXP | B29: Travel and expenses (Operating) | C29: 16555.22 | D29: =Sheet1!C27 -> 8188.52 | E29: =Sheet1!D27 -> 6222.27 | F29: =Sheet1!E27 -> 229.02 | G29: =Sheet1!F27 -> 0 | H29: =Sheet1!G27 -> 0
A30: FEXP | B30: Marketing Tech Stack (3rd party software subscriptions) | C30: 0 | D30: =Sheet1!C28 -> 508.96 | E30: =Sheet1!D28 -> 0 | F30: =Sheet1!E28 -> 0 | G30: =Sheet1!F28 -> 0 | H30: =Sheet1!G28 -> 0
A31: FEXP | B31: Events - Tradeshows and Conferences | C31: 166.4 | D31: =Sheet1!C29 -> 0 | E31: =Sheet1!D29 -> 250 | F31: =Sheet1!E29 -> 7779.88 | G31: =Sheet1!F29 -> 250 | H31: =Sheet1!G29 -> 250
A32: FEXP | B32: Travel/Meals (internal teammembers) | C32: 1956.29 | D32: =Sheet1!C30 -> 138.92 | E32: =Sheet1!D30 -> 1303.19 | F32: =Sheet1!E30 -> 1464.5 | G32: =Sheet1!F30 -> 29.59 | H32: =Sheet1!G30 -> 0
A33: FEXP | B33: Marketing Tech Stack | C33: 130 | D33: =Sheet1!C31 -> 0 | E33: =Sheet1!D31 -> 0 | F33: =Sheet1!E31 -> 0 | G33: =Sheet1!F31 -> 0 | H33: =Sheet1!G31 -> 0
A34: FEXP | B34: PR/Media | C34: 11.2 | D34: =Sheet1!C32 -> 1105.4 | E34: =Sheet1!D32 -> 1416 | F34: =Sheet1!E32 -> 1760.13 | G34: =Sheet1!F32 -> 0 | H34: =Sheet1!G32 -> 0
A35: FEXP | B35: Demand Generation | C35: 303.36 | D35: =Sheet1!C33 -> 68.06 | E35: =Sheet1!D33 -> 68.06 | F35: =Sheet1!E33 -> 783.88 | G35: =Sheet1!F33 -> 68.06 | H35: =Sheet1!G33 -> 68.06
A36: FEXP | B36: Software subscription (P&E) | C36: 767.81 | D36: =Sheet1!C34 -> 120 | E36: =Sheet1!D34 -> 120 | F36: =Sheet1!E34 -> -439.75 | G36: =Sheet1!F34 -> 164 | H36: =Sheet1!G34 -> 164
A37: FEXP | B37: Product and Engineering | D37: =Sheet1!C35 -> 0 | E37: =Sheet1!D35 -> 0 | F37: =Sheet1!E35 -> 0 | G37: =Sheet1!F35 -> 0 | H37: =Sheet1!G35 -> 0
A38: FEXP | B38: Product & Engineering Payroll & Employee Expenses | C38: 688.93 | D38: =Sheet1!C36 -> 0 | E38: =Sheet1!D36 -> 0 | F38: =Sheet1!E36 -> 0 | G38: =Sheet1!F36 -> 0 | H38: =Sheet1!G36 -> 0
A39: FEXP | B39: People cost- Product & Engineering | C39: 0 | D39: =Sheet1!C37 -> 1730.77 | E39: =Sheet1!D37 -> 1153.85 | F39: =Sheet1!E37 -> 1153.84 | G39: =Sheet1!F37 -> 5384.62 | H39: =Sheet1!G37 -> 0
A40: FEXP | B40: Payroll Taxes | D40: =Sheet1!C38 -> 159.12 | E40: =Sheet1!D38 -> 101.88 | F40: =Sheet1!E38 -> 103.04 | G40: =Sheet1!F38 -> 577.97 | H40: =Sheet1!G38 -> 0
A41: FEXP | B41: External Consultants | C41: 1744.3 | D41: =Sheet1!C39 -> 0 | E41: =Sheet1!D39 -> 0 | F41: =Sheet1!E39 -> 2467.25 | G41: =Sheet1!F39 -> 0 | H41: =Sheet1!G39 -> 0
A42: FEXP | B42: Software subscription | D42: =Sheet1!C40 -> 171.12 | E42: =Sheet1!D40 -> 171.69 | F42: =Sheet1!E40 -> 170.48 | G42: =Sheet1!F40 -> 436.27 | H42: =Sheet1!G40 -> 149.79
A43: FEXP | B43: Operations- People cost | C43: 8268.62 | D43: =Sheet1!C41 -> 4185 | E43: =Sheet1!D41 -> 2307.7 | F43: =Sheet1!E41 -> 2307.7 | G43: =Sheet1!F41 -> 1153.85 | H43: =Sheet1!G41 -> 0
A44: FEXP | B44: Payroll Taxes (G&A) | C44: 183 | D44: =Sheet1!C42 -> 662.84 | E44: =Sheet1!D42 -> 1024.98 | F44: =Sheet1!E42 -> 1403.12 | G44: =Sheet1!F42 -> 695.23 | H44: =Sheet1!G42 -> 0
A45: FEXP | B45: Employee Benefits & Insurance Expense (G&A) | C45: 4249.98 | D45: =Sheet1!C43 -> 0 | E45: =Sheet1!D43 -> 0 | F45: =Sheet1!E43 -> 120 | G45: =Sheet1!F43 -> 0 | H45: =Sheet1!G43 -> 0
A46: FEXP | B46: Executive Salary | C46: 3096.23 | D46: =Sheet1!C44 -> 18825.1 | E46: =Sheet1!D44 -> 13903.86 | F46: =Sheet1!E44 -> 16578.01 | G46: =Sheet1!F44 -> 7548.08 | H46: =Sheet1!G44 -> 0
A47: FEXP | B47: Consulting | C47: 366851.06 | D47: =Sheet1!C45 -> 7225.95 | E47: =Sheet1!D45 -> 5597.69 | F47: =Sheet1!E45 -> 5275.4 | G47: =Sheet1!F45 -> 0 | H47: =Sheet1!G45 -> 5343.05
A48: FEXP | B48: Professional Services (Legal, Recruitment, etc.) | C48: 10250 | D48: =Sheet1!C46 -> 0 | E48: =Sheet1!D46 -> 6000 | F48: =Sheet1!E46 -> 5111.25 | G48: =Sheet1!F46 -> 3000 | H48: =Sheet1!G46 -> 5050
A49: FEXP | B49: Rent and Utilities | D49: =Sheet1!C47 -> 1390.08 | E49: =Sheet1!D47 -> 1240.09 | F49: =Sheet1!E47 -> 2077.99 | G49: =Sheet1!F47 -> 1435 | H49: =Sheet1!G47 -> 12948.99
A50: FEXP | B50: Software subscription (G&A) | C50: -861.1 | D50: =Sheet1!C48 -> 1770.66 | E50: =Sheet1!D48 -> 642.83 | F50: =Sheet1!E48 -> 573.83 | G50: =Sheet1!F48 -> 2425.78 | H50: =Sheet1!G48 -> 471.42
A51: FEXP | B51: Payment Processing Costs | C51: -1651.29 | D51: =Sheet1!C49 -> 589.94 | E51: =Sheet1!D49 -> 385.9 | F51: =Sheet1!E49 -> 591.81 | G51: =Sheet1!F49 -> 525.39 | H51: =Sheet1!G49 -> -2852.4
A52: FEXP | B52: Other expenses | C52: 4311 | D52: =Sheet1!C50 -> 0 | E52: =Sheet1!D50 -> 36 | F52: =Sheet1!E50 -> 34.66 | G52: =Sheet1!F50 -> 25 | H52: =Sheet1!G50 -> 0
A53: FEXP | B53: Fundraising Cost | C53: 9007.01 | D53: =Sheet1!C51 -> 471.58 | E53: =Sheet1!D51 -> 484.94 | F53: =Sheet1!E51 -> 328.56 | G53: =Sheet1!F51 -> 473.67 | H53: =Sheet1!G51 -> 0
A54: FEXP | B54: Merchant account fees | D54: =Sheet1!C52 -> 0 | E54: =Sheet1!D52 -> 0 | F54: =Sheet1!E52 -> 0 | G54: =Sheet1!F52 -> 0 | H54: =Sheet1!G52 -> 46.05
B55: Other Income | C55: 1602.32
B56: Other Expenses | C56: 2015.06
B57: Current Assets | C57: -283.11
A58: CASH | B58: Bank Accounts | C58: 7879.4 | D58: 187516 | E58: 431402.99 | F58: 355934.64 | G58: 285246.15 | H58: 204486.69
A59: AR | B59: Accounts Receivable | C59: 0 | D59: 20391.44 | E59: 22654.12 | F59: 24916.8 | G59: 25396.8 | H59: 27659.48
A60: OCA | B60: Prepaid expenses | D60: -3200 | E60: 8240.06 | F60: 15300 | G60: 15759.45 | H60: 12309.45
A61: OCA | B61: Payments to deposit | D61: 0 | E61: 0 | F61: 0 | G61: 0 | H61: 0
A62: OCA | B62: Accrued Income | C62: 201839.13 | E62: 0 | F62: 60 | G62: 120 | H62: 0
B63: Non-Current Assets | C63: -164060.07
B64: Current Liabilities | C64: 123166.8
A65: OCL | B65: Credit Cards | C65: 231544.98 | D65: 26889.01 | E65: 13445.9 | F65: 21214.55 | G65: 12165.28 | H65: 4665.28
A66: OCL | B66: Short Term Loan Payable | E66: 0 | F66: 0 | G66: 0 | H66: 0
A67: OCL | B67: Short-term loans from partners | D67: 15925 | E67: 0 | F67: 0 | G67: 0 | H67: 0
B68: Non-Current Liabilities
B69: Convertible Notes | D69: 220000 | E69: 220000 | F69: 220000 | G69: 220000 | H69: 220000
B70: Equity
A71: OEQ | B71: Partner investments | D71: 1269750 | E71: 1619750 | F71: 1619750 | G71: 1619750 | H71: 1619750
A72: OEQ | B72: Partner distributions | D72: -5000 | E72: -5000 | F72: -5000 | G72: -5000 | H72: -5000
A73: RE | B73: Retained Earnings | D73: -1244527.6 | E73: -1244527.6 | F73: -1244527.6 | G73: -1244527.6 | H73: -1244527.6
A74: CE | B74: Income | D74: -78328.97 | E74: -141371.13 | F74: -215225.51 | G74: -275865.28 | H74: -350432.06

Sheet Sheet1
C2: Jan 2025 | D2: Feb 2025 | E2: Mar 2025 | F2: Apr 2025 | G2: May 2025
B4: Income
B5: Tier 3 | C5: 5813.85 | D5: 5813.85 | E5: 5873.85 | F5: 5873.85 | G5: 5248.18
B6: Other Optional Suites
B7: DCA Monitoring | E7: 0 | F7: 0 | G7: 0
B8: Implementation
B9: Tier 3
B10: Discounts | C10: 0 | D10: 0 | E10: 0 | F10: 0 | G10: 0
B11: Customer Discounts | C11: -565.67 | D11: -565.67 | E11: -565.67 | F11: -565.67 | G11: 0
B12: =#VALUE! -> #VALUE! | C12: 5248.18 | D12: 5248.18 | E12: 5308.18 | F12: 5308.18 | G12: 5248.18
B13: Implementation Costs
B14: Implementation Payroll & Employee Expenses
B15: Payroll Expenses (Implementation) | C15: 24418.58 | D15: 16601.56 | E15: 16491.56 | F15: 7355.78
B16: Payroll Taxes (Implementation) | C16: 1633.08 | D16: 1197.09 | E16: 1189.45 | F16: 594.72
B17: Server Hosting Charges | C17: 1364.26 | D17: 1530.25 | E17: 2616.47 | F17: 1600.58 | G17: 1596.51
B18: Customer Success Payroll & Employee Expenses
B19: Payroll Expenses | C19: 2957.89 | D19: 2203.27 | E19: 2175.77 | F19: 865.39
B20: Payroll Taxes | C20: 184.54 | D20: 141.48 | E20: 142.25 | F20: 71.13
B21: 500000 Cost of goods sold | C21: 30558.35 | D21: 21673.65 | E21: 22615.5 | F21: 10487.6 | G21: 1596.51
B22: Sales and Marketing Costs
B23: Operating Payroll & Employee Expenses | F23: 28172.03 | G23: 56579.49
B24: Payroll Expenses | C24: 5346.16 | D24: 3846.15 | E24: 5328 | F24: 1923.08
B25: Payroll Taxes | C25: 360.62 | D25: 339.61 | E25: 343.46 | F25: 171.73
B26: Employee Benefits & Insurance Expense | E26: 1001 | F26: 1001
B27: Travel and expenses (Operating) | C27: 8188.52 | D27: 6222.27 | E27: 229.02
B28: Marketing Tech Stack (3rd party software subscriptions) | C28: 508.96
B29: Events - Tradeshows and Conferences | D29: 250 | E29: 7779.88 | F29: 250 | G29: 250
B30: Travel/Meals (internal teammembers) | C30: 138.92 | D30: 1303.19 | E30: 1464.5 | F30: 29.59
B31: Marketing Tech Stack
B32: PR/Media | C32: 1105.4 | D32: 1416 | E32: 1760.13
B33: Demand Generation | C33: 68.06 | D33: 68.06 | E33: 783.88 | F33: 68.06 | G33: 68.06
B34: Software subscription | C34: 120 | D34: 120 | E34: -439.75 | F34: 164 | G34: 164
B35: Product and Engineering
B36: Product & Engineering Payroll & Employee Expenses
B37: People cost- Product & Engineering | C37: 1730.77 | D37: 1153.85 | E37: 1153.84 | F37: 5384.62
B38: Payroll Taxes | C38: 159.12 | D38: 101.88 | E38: 103.04 | F38: 577.97
B39: External Consultants | E39: 2467.25
B40: Software subscription | C40: 171.12 | D40: 171.69 | E40: 170.48 | F40: 436.27 | G40: 149.79
B41: Operations- People cost | C41: 4185 | D41: 2307.7 | E41: 2307.7 | F41: 1153.85
B42: Payroll Taxes | C42: 662.84 | D42: 1024.98 | E42: 1403.12 | F42: 695.23
B43: Employee Benefits & Insurance Expense | E43: 120
B44: Executive Salary | C44: 18825.1 | D44: 13903.86 | E44: 16578.01 | F44: 7548.08
B45: Consulting | C45: 7225.95 | D45: 5597.69 | E45: 5275.4 | G45: 5343.05
B46: Professional Services (Legal, Recruitment, etc.) | D46: 6000 | E46: 5111.25 | F46: 3000 | G46: 5050
B47: Rent and Utilities | C47: 1390.08 | D47: 1240.09 | E47: 2077.99 | F47: 1435 | G47: 12948.99
B48: Software subscription | C48: 1770.66 | D48: 642.83 | E48: 573.83 | F48: 2425.78 | G48: 471.42
B49: Payment Processing Costs | C49: 589.94 | D49: 385.9 | E49: 591.81 | F49: 525.39 | G49: -2852.4
B50: Other expenses | D50: 36 | E50: 34.66 | F50: 25
B51: Fundraising Cost | C51: 471.58 | D51: 484.94 | E51: 328.56 | F51: 473.67
B52: account fees | G52: 46.05

Sheet KPI Sheet
A1: KPI | B1: This Month | C1: Last Month | D1: Variance | E1: Variance % | F1: YTD
A2: Core Saas Metrics
A3: MRR | B3: ='Financial Data'!H7+'Financial Data'!H10 -> 5248.18 | C3: ='Financial Data'!G7+'Financial Data'!G10 -> 5873.85 | D3: =(B3-C3) -> -625.67 | E3: -0.11 | F3: 5665
A4: ARR | B4: =B3*12 -> 62978.16 | C4: =C3*12 -> 70486.2 | D4: =(B4-C4) -> -7508.04 | E4: -0.11 | F4: =F3*12 -> 67980
A5: Sales & Growth
A6: CAC | B6: 0 | C6: 0 | D6: =(B6-C6) -> 0 | E6: =IFERROR(D6/C6,0) -> 0 | F6: 0
A7: LTV | B7: 328 | C7: 328 | D7: =(B7-C7) -> 0 | E7: =IFERROR(D7/C7,0) -> 0 | F7: 0
A8: LTV Ratio | B8: 0 | C8: 0 | D8: =(B8-C8) -> 0 | E8: =IFERROR(D8/C8,0) -> 0 | F8: 0
A9: Go-to-Market
A10: Total Customer Count | B10: =SUM(B11:B12) -> 16 | C10: =SUM(C11:C12) -> 16 | D10: =(B10-C10) -> 0 | E10: =IFERROR(D10/C10,0) -> 0 | F10: =SUM(F11:F12) -> 16
A11: Live | B11: 16 | C11: 16 | D11: =(B11-C11) -> 0 | E11: =IFERROR(D11/C11,0) -> 0 | F11: 16
A12: Implementation | B12: 0 | C12: 0 | D12: =(B12-C12) -> 0 | E12: =IFERROR(D12/C12,0) -> 0 | F12: 0
A13: Capital Efficiency
A14: Cash RunWay | B14: 6 | C14: 3 | D14: =(B14-C14) -> 3 | E14: 1 | F14: 1
A15: Burn Rate | B15: 358522 | C15: 291420 | D15: =(B15-C15) -> 67102 | E15: 0.23 | F15: 358522
A16: Profitability
A17: Gross Margin | B17: -0.15 | C17: -3.93 | D17: =B17-C17 -> 3.78 | E17: -0.96 | F17: 4.1075
A18: Operating Margin | B18: -4.25 | C18: -16.34 | D18: =B18-C18 -> 12.09 | E18: -0.74 | F18: 15.0746
